adbench/__init__.py
adbench/myutils.py
adbench/run.py
adbench/baseline/PyOD.py
adbench/baseline/Supervised.py
adbench/baseline/__init__.py
adbench/baseline/Customized/__init__.py
adbench/baseline/Customized/fit.py
adbench/baseline/Customized/model.py
adbench/baseline/Customized/run.py
adbench/baseline/DAGMM/__init__.py
adbench/baseline/DAGMM/forward_step.py
adbench/baseline/DAGMM/main.py
adbench/baseline/DAGMM/model.py
adbench/baseline/DAGMM/preprocess.py
adbench/baseline/DAGMM/run.py
adbench/baseline/DAGMM/test.py
adbench/baseline/DAGMM/train.py
adbench/baseline/DAGMM/utils/__init__.py
adbench/baseline/DAGMM/utils/utils.py
adbench/baseline/DeepSAD/__init__.py
adbench/baseline/DeepSAD/src/__init__.py
adbench/baseline/DeepSAD/src/baseline_SemiDGM.py
adbench/baseline/DeepSAD/src/baseline_isoforest.py
adbench/baseline/DeepSAD/src/baseline_kde.py
adbench/baseline/DeepSAD/src/baseline_ocsvm.py
adbench/baseline/DeepSAD/src/baseline_ssad.py
adbench/baseline/DeepSAD/src/deepsad.py
adbench/baseline/DeepSAD/src/run.py
adbench/baseline/DeepSAD/src/base/__init__.py
adbench/baseline/DeepSAD/src/base/base_dataset.py
adbench/baseline/DeepSAD/src/base/base_net.py
adbench/baseline/DeepSAD/src/base/base_trainer.py
adbench/baseline/DeepSAD/src/base/odds_dataset.py
adbench/baseline/DeepSAD/src/base/torchvision_dataset.py
adbench/baseline/DeepSAD/src/baselines/SemiDGM.py
adbench/baseline/DeepSAD/src/baselines/__init__.py
adbench/baseline/DeepSAD/src/baselines/isoforest.py
adbench/baseline/DeepSAD/src/baselines/kde.py
adbench/baseline/DeepSAD/src/baselines/ocsvm.py
adbench/baseline/DeepSAD/src/baselines/ssad.py
adbench/baseline/DeepSAD/src/baselines/shallow_ssad/__init__.py
adbench/baseline/DeepSAD/src/baselines/shallow_ssad/ssad_convex.py
adbench/baseline/DeepSAD/src/datasets/__init__.py
adbench/baseline/DeepSAD/src/datasets/cifar10.py
adbench/baseline/DeepSAD/src/datasets/fmnist.py
adbench/baseline/DeepSAD/src/datasets/main.py
adbench/baseline/DeepSAD/src/datasets/mnist.py
adbench-0.1.11.dist-info/LICENSE
adbench-0.1.11.dist-info/METADATA
adbench-0.1.11.dist-info/WHEEL
adbench-0.1.11.dist-info/top_level.txt
adbench-0.1.11.dist-info/RECORD
